decoutilities/__init__.py
decoutilities/components/___init__.py
decoutilities/components/__init__.py
decoutilities/components/checkmark.py
decoutilities/components/input.py
decoutilities/components/selector.py
decoutilities/config/__init__.py
decoutilities/config/config.py
decoutilities/config/configContainer.py
decoutilities/data/__init__.py
decoutilities/data/dataEncryptor.py
decoutilities/data/keyManager.py
decoutilities/inject/__init__.py
decoutilities/inject/injector.py
decoutilities/logger/__init__.py
decoutilities/queue/__init__.py
decoutilities/screenUtils/__init__.py
decoutilities/screenUtils/saver.py
decoutilities/screenUtils/screen.py
decoutilities/screenUtils/titler.py
decoutilities/screenUtils/pseudoTerminal/__init__.py
decoutilities/screenUtils/pseudoTerminal/cd.py
decoutilities/screenUtils/pseudoTerminal/command.py
decoutilities/textUtils/__init__.py
decoutilities-0.3.6.dist-info/LICENSE
decoutilities-0.3.6.dist-info/METADATA
decoutilities-0.3.6.dist-info/WHEEL
decoutilities-0.3.6.dist-info/top_level.txt
decoutilities-0.3.6.dist-info/RECORD
