Metadata-Version: 2.1
Name: decoutilities
Version: 0.3.6
Summary: Enhance the readability of your code with decorators and simplify the creation of configuration files.
Author: Hugo Torres
Author-email: contact@redactado.es
Classifier: Programming Language :: Python :: 3
Classifier: License :: OSI Approved :: MIT License
Classifier: Operating System :: OS Independent
Requires-Python: >=3.6
License-File: LICENSE
